RTL/spi_slave.v
`timescale 1ns/1ps

// -----------------------------------------------------------------------------
// File        : spi_slave.v
// Project     : Lab 2 - SPI Communication
// Description : SPI Slave, 8-bit full-duplex, SPI Mode 0 (CPOL=0, CPHA=0),
//               MSB-first. Single clock domain: REFCLK. Active-low reset.
// Notes       : LOAD is treated as a synchronous data-enable, not as a clock.
//               SCLK and CS are sampled on REFCLK and SCLK rising edges are
//               detected internally. MISO is combinational from the current TX
//               bit so it is valid before the master sampling edge.
// -----------------------------------------------------------------------------

module spi_slave (
    input             REFCLK,
    input             RST_N,
    input             SCLK,
    input             CS,       // active-LOW chip select
    input             LOAD,     // active-HIGH synchronous load enable
    input      [7:0]  data_in,
    input             MOSI,
    output            MISO,
    output reg [7:0]  data_out,
    output            READY
);

    reg [7:0] tx_shift;
    reg [7:0] rx_shift;
    reg [2:0] bit_cnt;
    reg       active;
    reg       sclk_d;
    wire      cs_active;

    wire sclk_rise = (SCLK == 1'b1) && (sclk_d == 1'b0);

    assign cs_active = (CS == 1'b0);
    assign READY     = (!cs_active) && (active == 1'b0);
    assign MISO      = cs_active ? tx_shift[bit_cnt] : 1'b0;

    always @(posedge REFCLK or negedge RST_N) begin
        if (!RST_N) begin
            tx_shift <= 8'h00;
            rx_shift <= 8'h00;
            bit_cnt  <= 3'd7;
            active   <= 1'b0;
            sclk_d   <= 1'b0;
            data_out   <= 8'h00;
        end else begin
            sclk_d <= SCLK;

            // Synchronous load. This replaces always @(posedge LOAD), which
            // would incorrectly treat a data-enable as a generated clock.
            if (LOAD && READY) begin
                tx_shift <= data_in;
            end

            if (!cs_active) begin
                active  <= 1'b0;
                bit_cnt <= 3'd7;
            end else begin
                active <= 1'b1;

                if (sclk_rise) begin
                    rx_shift[bit_cnt] <= MOSI;

                    if (bit_cnt == 3'd0) begin
                        data_out  <= {rx_shift[7:1], MOSI};
                        bit_cnt <= 3'd7;
                        active  <= 1'b0;
                    end else begin
                        bit_cnt <= bit_cnt - 3'd1;
                    end
                end
            end
        end
    end
endmodule

RTL/spi_master.v
`timescale 1ns/1ps

// -----------------------------------------------------------------------------
// File        : spi_master.v
// Project     : Lab 2 - SPI Communication
// Description : SPI Master, 8-bit full-duplex, SPI Mode 0 (CPOL=0, CPHA=0),
//               MSB-first. Single clock domain: REFCLK. Active-low reset.
// Notes       : CNTL=00 no-op, CNTL=01 load TX data, CNTL=10 store slave
//               address, CNTL=11 start transfer. SS is active only while the
//               transfer is running; it returns to 8'hFF in IDLE/WAIT_RELEASE.
// -----------------------------------------------------------------------------

module spi_master (
    input             REFCLK,
    input             RST_N,
    input      [7:0]  data_in,
    input      [2:0]  select_ss,
    input      [1:0]  CNTL,
    input             MISO,
    output reg [7:0]  data_out,
    output reg        READY,
    output reg        MOSI,
    output reg        SCLK,
    output reg [7:0]  SS
);

    localparam ST_IDLE         = 2'd0;
    localparam ST_TRANSFER     = 2'd1;
    localparam ST_WAIT_RELEASE = 2'd2;

    reg [1:0] state;
    reg [7:0] tx_data;
    reg [7:0] rx_shift;
    reg [7:0] selected_ss;
    reg [2:0] bit_cnt;
    reg       sclk_level;

    always @(posedge REFCLK or negedge RST_N) begin
        if (!RST_N) begin
            state       <= ST_IDLE;
            tx_data     <= 8'h00;
            rx_shift    <= 8'h00;
            selected_ss <= 8'hFF;
            bit_cnt     <= 3'd7;
            sclk_level  <= 1'b0;
            data_out    <= 8'h00;
            READY       <= 1'b1;
            MOSI        <= 1'b0;
            SCLK        <= 1'b0;
            SS          <= 8'hFF;
        end else begin
            case (state)
                ST_IDLE: begin
                    READY      <= 1'b1;
                    SCLK       <= 1'b0;
                    MOSI       <= 1'b0;
                    SS         <= 8'hFF;
                    sclk_level <= 1'b0;

                    case (CNTL)
                        2'b00: begin
                            // No operation.
                        end

                        2'b01: begin
                            // Load data to be transmitted when the master is ready.
                            tx_data <= data_in;
                        end

                        2'b10: begin
                            // Store the slave-select decode. Do not assert SS yet.
                            selected_ss <= ~(8'b0000_0001 << select_ss);
                        end

                        2'b11: begin
                            // Start one 8-bit full-duplex transfer.
                            state       <= ST_TRANSFER;
                            READY       <= 1'b0;
                            bit_cnt     <= 3'd7;
                            rx_shift    <= 8'h00;
                            MOSI        <= tx_data[7];
                            SCLK        <= 1'b0;
                            sclk_level  <= 1'b0;
                            SS          <= selected_ss;
                        end
                    endcase
                end

                ST_TRANSFER: begin
                    READY <= 1'b0;
                    SS    <= selected_ss;

                    if (sclk_level == 1'b0) begin
                        // SPI Mode 0 rising edge: sample MISO.
                        SCLK              <= 1'b1;
                        sclk_level        <= 1'b1;
                        rx_shift[bit_cnt] <= MISO;

                        if (bit_cnt == 3'd0) begin
                            data_out <= {rx_shift[7:1], MISO};
                        end
                    end else begin
                        // SPI Mode 0 falling edge: prepare the next MOSI bit or finish.
                        SCLK       <= 1'b0;
                        sclk_level <= 1'b0;

                        if (bit_cnt == 3'd0) begin
                            state <= ST_WAIT_RELEASE;
                            MOSI  <= 1'b0;
                            SS    <= 8'hFF;
                        end else begin
                            bit_cnt <= bit_cnt - 3'd1;
                            MOSI    <= tx_data[bit_cnt - 3'd1];
                        end
                    end
                end

                ST_WAIT_RELEASE: begin
                    SCLK <= 1'b0;
                    MOSI <= 1'b0;
                    SS   <= 8'hFF;

                    // Avoid repeated transfers if CNTL is still held at 2'b11.
                    if (CNTL != 2'b11) begin
                        READY <= 1'b1;
                        state <= ST_IDLE;
                    end else begin
                        READY <= 1'b0;
                    end
                end

                default: begin
                    state <= ST_IDLE;
                end
            endcase
        end
    end
endmodule

RTL/spi_communication.v
`timescale 1ns/1ps

// -----------------------------------------------------------------------------
// File        : spi_communication.v
// Project     : Lab 2 - SPI Communication
// Description : Top-level module integrating one SPI Master and one SPI Slave.
//               Both submodules use REFCLK and active-low reset RST_N.
// -----------------------------------------------------------------------------

module spi_communication (
    input             REFCLK,
    input             RST_N,

    // Master control/data interface
    input      [7:0]  M_INPUT,
    input      [2:0]  M_SELECT_SS,
    input      [1:0]  M_CNTL,
    output     [7:0]  M_OUTPUT,
    output            M_READY,

    // Slave control/data interface
    input      [7:0]  S_INPUT,
    input             S_LOAD,
    output     [7:0]  S_OUTPUT,
    output            S_READY,

    // Exposed SPI wires for waveform observation
    output            MOSI,
    output            MISO,
    output            SCLK,
    output     [7:0]  SS
);

    wire mosi_w;
    wire miso_w;
    wire sclk_w;
    wire [7:0] ss_w;

    // This complete module integrates one slave on SS[0]. Other SS bits are
    // still decoded by the master and exposed for observation.
    wire cs_slave0 = ss_w[0];

    spi_master u_spi_master (
        .REFCLK (REFCLK),
        .RST_N  (RST_N),
        .data_in   (M_INPUT),
        .select_ss (M_SELECT_SS),
        .CNTL   (M_CNTL),
        .MISO   (miso_w),
        .data_out (M_OUTPUT),
        .READY  (M_READY),
        .MOSI   (mosi_w),
        .SCLK   (sclk_w),
        .SS     (ss_w)
    );

    spi_slave u_spi_slave (
        .REFCLK (REFCLK),
        .RST_N  (RST_N),
        .SCLK   (sclk_w),
        .CS     (cs_slave0),
        .LOAD   (S_LOAD),
        .data_in  (S_INPUT),
        .MOSI   (mosi_w),
        .MISO   (miso_w),
        .data_out (S_OUTPUT),
        .READY  (S_READY)
    );

    assign MOSI = mosi_w;
    assign MISO = miso_w;
    assign SCLK = sclk_w;
    assign SS   = ss_w;
endmodule

static_tb/tb_spi_communication.v
`timescale 1ns/1ps

module tb_spi_communication;
    reg         REFCLK;
    reg         RST_N;
    reg  [7:0]  M_INPUT;
    reg  [2:0]  M_SELECT_SS;
    reg  [1:0]  M_CNTL;
    wire [7:0]  M_OUTPUT;
    wire        M_READY;

    reg  [7:0]  S_INPUT;
    reg         S_LOAD;
    wire [7:0]  S_OUTPUT;
    wire        S_READY;

    wire        MOSI;
    wire        MISO;
    wire        SCLK;
    wire [7:0]  SS;

    integer pass_count;
    integer fail_count;

    spi_communication dut (
        .REFCLK(REFCLK), .RST_N(RST_N),
        .M_INPUT(M_INPUT), .M_SELECT_SS(M_SELECT_SS), .M_CNTL(M_CNTL), .M_OUTPUT(M_OUTPUT), .M_READY(M_READY),
        .S_INPUT(S_INPUT), .S_LOAD(S_LOAD), .S_OUTPUT(S_OUTPUT), .S_READY(S_READY),
        .MOSI(MOSI), .MISO(MISO), .SCLK(SCLK), .SS(SS)
    );

    initial REFCLK = 1'b0;
    always #5 REFCLK = ~REFCLK;

    task check_bit;
        input condition;
        input [1023:0] message;
        begin
            if (condition) begin
                $display("PASS | %0s", message);
                pass_count = pass_count + 1;
            end else begin
                $display("FAIL | %0s", message);
                fail_count = fail_count + 1;
            end
        end
    endtask

    task apply_reset;
        begin
            RST_N = 1'b0;
            M_INPUT = 8'h00;
            M_SELECT_SS = 3'd0;
            M_CNTL  = 2'b00;
            S_INPUT = 8'h00;
            S_LOAD  = 1'b0;
            repeat (3) @(negedge REFCLK);
            RST_N = 1'b1;
            repeat (2) @(negedge REFCLK);
        end
    endtask

    task load_slave_data;
        input [7:0] data;
        begin
            @(negedge REFCLK);
            S_INPUT = data;
            S_LOAD  = 1'b1;
            @(negedge REFCLK);
            S_LOAD  = 1'b0;
            @(negedge REFCLK);
        end
    endtask

    task load_master_data;
        input [7:0] data;
        begin
            @(negedge REFCLK);
            M_INPUT = data;
            M_CNTL  = 2'b01;
            @(negedge REFCLK);
            M_CNTL  = 2'b00;
            @(negedge REFCLK);
        end
    endtask

    task select_slave;
        input [2:0] addr;
        begin
            @(negedge REFCLK);
            M_SELECT_SS = addr;
            M_CNTL      = 2'b10;
            @(negedge REFCLK);
            M_CNTL  = 2'b00;
            @(negedge REFCLK);
        end
    endtask

    task start_transfer;
        input [7:0] expected_ss;
        begin
            @(negedge REFCLK);
            M_CNTL = 2'b11;
            @(posedge REFCLK); // DUT samples the start command here.
            @(negedge REFCLK);
            check_bit(M_READY === 1'b0, "transfer drives master READY LOW");
            check_bit(SS === expected_ss, "SS is asserted only while transfer is active");
            M_CNTL = 2'b00;
            wait (M_READY === 1'b1);
            @(negedge REFCLK);
            check_bit(SS === 8'hFF, "SS returns inactive after transfer");
        end
    endtask

    initial begin
        $dumpfile("tb_spi_communication.vcd");
        $dumpvars(0, tb_spi_communication);

        pass_count = 0;
        fail_count = 0;

        apply_reset;
        $display("\n=== tb_spi_communication ===");

        check_bit(M_READY === 1'b1, "TC_TOP_001 master READY is HIGH in idle after reset");
        check_bit(S_READY === 1'b1, "TC_TOP_002 slave READY is HIGH in idle after reset");
        check_bit(SS === 8'hFF, "TC_TOP_003 SS is inactive before any transfer");

        load_slave_data(8'h3C);
        select_slave(3'd0);
        check_bit(SS === 8'hFF, "TC_TOP_004 selected slave is stored; SS stays inactive before TX");
        load_master_data(8'hA5);
        start_transfer(8'hFE);
        check_bit(M_OUTPUT === 8'h3C, "TC_TOP_005 master receives slave byte 0x3C");
        check_bit(S_OUTPUT === 8'hA5, "TC_TOP_006 slave receives master byte 0xA5");
        check_bit(M_READY === 1'b1, "TC_TOP_007 master READY returns HIGH after transfer");
        check_bit(S_READY === 1'b1, "TC_TOP_008 slave READY returns HIGH after transfer");

        // Consecutive transfer after READY/CNTL release.
        load_slave_data(8'h81);
        select_slave(3'd0);
        load_master_data(8'h7E);
        start_transfer(8'hFE);
        check_bit(M_OUTPUT === 8'h81, "TC_TOP_009 second transfer M_OUTPUT=0x81");
        check_bit(S_OUTPUT === 8'h7E, "TC_TOP_010 second transfer S_OUTPUT=0x7E");

        // Explicit complete-module loopback-style test: same byte loaded on both sides.
        load_slave_data(8'h5A);
        select_slave(3'd0);
        load_master_data(8'h5A);
        start_transfer(8'hFE);
        check_bit(M_OUTPUT === 8'h5A, "TC_TOP_011 loopback-style master receives 0x5A");
        check_bit(S_OUTPUT === 8'h5A, "TC_TOP_012 loopback-style slave receives 0x5A");

        select_slave(3'd3);
        check_bit(SS === 8'hFF, "TC_TOP_013 selecting unconnected slave stores address but keeps SS inactive before TX");

        $display("=== tb_spi_communication result: %0d PASS / %0d FAIL ===", pass_count, fail_count);
        if (fail_count == 0) $display("TB_RESULT: PASS");
        else                 $display("TB_RESULT: FAIL");
        #30;
        $finish;
    end
endmodule

tb_spi_communication.vcd
$version Generated by VerilatedVcd $end
$timescale 1ps $end
 $scope module TOP $end
  $scope module tb_spi_communication $end
   $var wire 1 A REFCLK $end
   $var wire 1 # RST_N $end
   $var wire 8 $ M_INPUT [7:0] $end
   $var wire 3 % M_SELECT_SS [2:0] $end
   $var wire 2 & M_CNTL [1:0] $end
   $var wire 8 + M_OUTPUT [7:0] $end
   $var wire 1 , M_READY $end
   $var wire 8 ' S_INPUT [7:0] $end
   $var wire 1 ( S_LOAD $end
   $var wire 8 - S_OUTPUT [7:0] $end
   $var wire 1 . S_READY $end
   $var wire 1 / MOSI $end
   $var wire 1 0 MISO $end
   $var wire 1 1 SCLK $end
   $var wire 8 2 SS [7:0] $end
   $var wire 32 ) pass_count [31:0] $end
   $var wire 32 * fail_count [31:0] $end
   $scope module dut $end
    $var wire 1 A REFCLK $end
    $var wire 1 # RST_N $end
    $var wire 8 $ M_INPUT [7:0] $end
    $var wire 3 % M_SELECT_SS [2:0] $end
    $var wire 2 & M_CNTL [1:0] $end
    $var wire 8 + M_OUTPUT [7:0] $end
    $var wire 1 , M_READY $end
    $var wire 8 ' S_INPUT [7:0] $end
    $var wire 1 ( S_LOAD $end
    $var wire 8 - S_OUTPUT [7:0] $end
    $var wire 1 . S_READY $end
    $var wire 1 / MOSI $end
    $var wire 1 0 MISO $end
    $var wire 1 1 SCLK $end
    $var wire 8 2 SS [7:0] $end
    $var wire 1 / mosi_w $end
    $var wire 1 0 miso_w $end
    $var wire 1 1 sclk_w $end
    $var wire 8 2 ss_w [7:0] $end
    $var wire 1 3 cs_slave0 $end
    $scope module u_spi_master $end
     $var wire 1 A REFCLK $end
     $var wire 1 # RST_N $end
     $var wire 8 $ data_in [7:0] $end
     $var wire 3 % select_ss [2:0] $end
     $var wire 2 & CNTL [1:0] $end
     $var wire 1 0 MISO $end
     $var wire 8 + data_out [7:0] $end
     $var wire 1 , READY $end
     $var wire 1 / MOSI $end
     $var wire 1 1 SCLK $end
     $var wire 8 2 SS [7:0] $end
     $var wire 2 B ST_IDLE [1:0] $end
     $var wire 2 C ST_TRANSFER [1:0] $end
     $var wire 2 D ST_WAIT_RELEASE [1:0] $end
     $var wire 2 4 state [1:0] $end
     $var wire 8 5 tx_data [7:0] $end
     $var wire 8 6 rx_shift [7:0] $end
     $var wire 8 7 selected_ss [7:0] $end
     $var wire 3 8 bit_cnt [2:0] $end
     $var wire 1 9 sclk_level $end
    $upscope $end
    $scope module u_spi_slave $end
     $var wire 1 A REFCLK $end
     $var wire 1 # RST_N $end
     $var wire 1 1 SCLK $end
     $var wire 1 3 CS $end
     $var wire 1 ( LOAD $end
     $var wire 8 ' data_in [7:0] $end
     $var wire 1 / MOSI $end
     $var wire 1 0 MISO $end
     $var wire 8 - data_out [7:0] $end
     $var wire 1 . READY $end
     $var wire 8 : tx_shift [7:0] $end
     $var wire 8 ; rx_shift [7:0] $end
     $var wire 3 < bit_cnt [2:0] $end
     $var wire 1 = active $end
     $var wire 1 > sclk_d $end
     $var wire 1 ? cs_active $end
     $var wire 1 @ sclk_rise $end
    $upscope $end
   $upscope $end
  $upscope $end
 $upscope $end
$enddefinitions $end


#0
0#
b00000000 $
b000 %
b00 &
b00000000 '
0(
b00000000000000000000000000000000 )
b00000000000000000000000000000000 *
b00000000 +
0,
b00000000 -
0.
0/
00
01
b00000000 2
03
b00 4
b00000000 5
b00000000 6
b00000000 7
b000 8
09
b00000000 :
b00000000 ;
b000 <
0=
0>
1?
0@
0A
b00 B
b01 C
b10 D
#5000
1,
1.
b11111111 2
13
b11111111 7
b111 8
b111 <
0?
1A
#10000
0A
#15000
1A
#20000
0A
#25000
1A
#30000
1#
0A
#35000
1A
#40000
0A
#45000
1A
#50000
b00000000000000000000000000000011 )
0A
#55000
1A
#60000
b00111100 '
1(
0A
#65000
b00111100 :
1A
#70000
0(
0A
#75000
1A
#80000
0A
#85000
1A
#90000
b10 &
0A
#95000
b11111110 7
1A
#100000
b00 &
0A
#105000
1A
#110000
b00000000000000000000000000000100 )
0A
#115000
1A
#120000
b10100101 $
b01 &
0A
#125000
b10100101 5
1A
#130000
b00 &
0A
#135000
1A
#140000
0A
#145000
1A
#150000
b11 &
0A
#155000
0,
0.
1/
b11111110 2
03
b01 4
1?
1A
#160000
b00 &
b00000000000000000000000000000110 )
0A
#165000
11
19
1=
1@
1A
#170000
0A
#175000
0/
01
b110 8
09
b10000000 ;
b110 <
1>
0@
1A
#180000
0A
#185000
11
19
0>
1@
1A
#190000
0A
#195000
1/
10
01
b101 8
09
b101 <
1>
0@
1A
#200000
0A
#205000
11
b00100000 6
19
0>
1@
1A
#210000
0A
#215000
0/
01
b100 8
09
b10100000 ;
b100 <
1>
0@
1A
#220000
0A
#225000
11
b00110000 6
19
0>
1@
1A
#230000
0A
#235000
01
b011 8
09
b011 <
1>
0@
1A
#240000
0A
#245000
11
b00111000 6
19
0>
1@
1A
#250000
0A
#255000
1/
01
b010 8
09
b010 <
1>
0@
1A
#260000
0A
#265000
11
b00111100 6
19
0>
1@
1A
#270000
0A
#275000
0/
00
01
b001 8
09
b10100100 ;
b001 <
1>
0@
1A
#280000
0A
#285000
11
19
0>
1@
1A
#290000
0A
#295000
1/
01
b000 8
09
b000 <
1>
0@
1A
#300000
0A
#305000
b00111100 +
11
19
0>
1@
1A
#310000
0A
#315000
b10100101 -
1.
0/
01
b11111111 2
13
b10 4
09
b10100101 ;
b111 <
0=
1>
0?
0@
1A
#320000
0A
#325000
1,
b00 4
0>
1A
#330000
b00000000000000000000000000001011 )
0A
#335000
1A
#340000
b10000001 '
1(
0A
#345000
b10000001 :
1A
#350000
0(
0A
#355000
1A
#360000
0A
#365000
1A
#370000
b10 &
0A
#375000
1A
#380000
b00 &
0A
#385000
1A
#390000
0A
#395000
1A
#400000
b01111110 $
b01 &
0A
#405000
b01111110 5
1A
#410000
b00 &
0A
#415000
1A
#420000
0A
#425000
1A
#430000
b11 &
0A
#435000
0,
0.
10
b11111110 2
03
b01 4
b00000000 6
b111 8
1?
1A
#440000
b00 &
b00000000000000000000000000001101 )
0A
#445000
11
b10000000 6
19
1=
1@
1A
#450000
0A
#455000
1/
00
01
b110 8
09
b00100101 ;
b110 <
1>
0@
1A
#460000
0A
#465000
11
19
0>
1@
1A
#470000
0A
#475000
01
b101 8
09
b01100101 ;
b101 <
1>
0@
1A
#480000
0A
#485000
11
19
0>
1@
1A
#490000
0A
#495000
01
b100 8
09
b100 <
1>
0@
1A
#500000
0A
#505000
11
19
0>
1@
1A
#510000
0A
#515000
01
b011 8
09
b01110101 ;
b011 <
1>
0@
1A
#520000
0A
#525000
11
19
0>
1@
1A
#530000
0A
#535000
01
b010 8
09
b01111101 ;
b010 <
1>
0@
1A
#540000
0A
#545000
11
19
0>
1@
1A
#550000
0A
#555000
01
b001 8
09
b001 <
1>
0@
1A
#560000
0A
#565000
11
19
0>
1@
1A
#570000
0A
#575000
0/
10
01
b000 8
09
b01111111 ;
b000 <
1>
0@
1A
#580000
0A
#585000
b10000001 +
11
b10000001 6
19
0>
1@
1A
#590000
0A
#595000
b01111110 -
1.
00
01
b11111111 2
13
b10 4
09
b01111110 ;
b111 <
0=
1>
0?
0@
1A
#600000
0A
#605000
1,
b00 4
0>
1A
#610000
b00000000000000000000000000010000 )
0A
#615000
1A
#620000
b01011010 '
1(
0A
#625000
b01011010 :
1A
#630000
0(
0A
#635000
1A
#640000
0A
#645000
1A
#650000
b10 &
0A
#655000
1A
#660000
b00 &
0A
#665000
1A
#670000
0A
#675000
1A
#680000
b01011010 $
b01 &
0A
#685000
b01011010 5
1A
#690000
b00 &
0A
#695000
1A
#700000
0A
#705000
1A
#710000
b11 &
0A
#715000
0,
0.
b11111110 2
03
b01 4
b00000000 6
b111 8
1?
1A
#720000
b00 &
b00000000000000000000000000010010 )
0A
#725000
11
19
1=
1@
1A
#730000
0A
#735000
1/
10
01
b110 8
09
b110 <
1>
0@
1A
#740000
0A
#745000
11
b01000000 6
19
0>
1@
1A
#750000
0A
#755000
0/
00
01
b101 8
09
b101 <
1>
0@
1A
#760000
0A
#765000
11
19
0>
1@
1A
#770000
0A
#775000
1/
10
01
b100 8
09
b01011110 ;
b100 <
1>
0@
1A
#780000
0A
#785000
11
b01010000 6
19
0>
1@
1A
#790000
0A
#795000
01
b011 8
09
b011 <
1>
0@
1A
#800000
0A
#805000
11
b01011000 6
19
0>
1@
1A
#810000
0A
#815000
0/
00
01
b010 8
09
b010 <
1>
0@
1A
#820000
0A
#825000
11
19
0>
1@
1A
#830000
0A
#835000
1/
10
01
b001 8
09
b01011010 ;
b001 <
1>
0@
1A
#840000
0A
#845000
11
b01011010 6
19
0>
1@
1A
#850000
0A
#855000
0/
00
01
b000 8
09
b000 <
1>
0@
1A
#860000
0A
#865000
b01011010 +
11
19
0>
1@
1A
#870000
0A
#875000
b01011010 -
1.
01
b11111111 2
13
b10 4
09
b111 <
0=
1>
0?
0@
1A
#880000
0A
#885000
1,
b00 4
0>
1A
#890000
b00000000000000000000000000010101 )
0A
#895000
1A
#900000
b011 %
b10 &
0A
#905000
b11110111 7
1A
#910000
b00 &
0A
#915000
1A
#920000
b00000000000000000000000000010110 )
0A
